proverb/__init__.py
proverb/command_line.py
proverb/saying.py
proverb-0.1.dist-info/DESCRIPTION.rst
proverb-0.1.dist-info/METADATA
proverb-0.1.dist-info/RECORD
proverb-0.1.dist-info/WHEEL
proverb-0.1.dist-info/entry_points.txt
proverb-0.1.dist-info/metadata.json
proverb-0.1.dist-info/top_level.txt
